BangunDatar/__init__.py
BangunDatar/jajar_genjang.py
BangunDatar/persegi.py
BangunDatar/persegi_panjang.py
BangunDatar/trapesium.py
BangunRuang/__init__.py
BangunRuang/balok.py
BangunRuang/bola.py
BangunRuang/kerucut.py
BangunRuang/kubus.py
BangunRuang/limas_segi_empat.py
BangunRuang/tabung.py
bangunDatar_bangunRuang-0.0.13.dist-info/LICENCE.txt
bangunDatar_bangunRuang-0.0.13.dist-info/METADATA
bangunDatar_bangunRuang-0.0.13.dist-info/WHEEL
bangunDatar_bangunRuang-0.0.13.dist-info/top_level.txt
bangunDatar_bangunRuang-0.0.13.dist-info/RECORD
